Workbook

Sheet Nomina
A1: ID Empleado | B1: Nombre | C1: Cargo | D1: Salario Base | E1: Bonificación | F1: Auxilio | G1: Descuentos | H1: Neto Pagado
A2: 1001 | B2: Ana Gómez | C2: Administradora | D2: 2800000 | E2: 200000 | F2: 150000 | G2: 0 | H2: 2850000
A3: 1002 | B3: Carlos Pérez | C3: Analista | D3: 3200000 | E3: 250000 | F3: 180000 | G3: 0 | H3: 3270000
A4: 1003 | B4: Laura Rodríguez | C4: Contadora | D4: 3500000 | E4: 300000 | F4: 200000 | G4: 100000 | H4: 3500000
A5: 1004 | B5: Juan Martínez | C5: Desarrollador | D5: 4200000 | E5: 350000 | F5: 250000 | G5: 0 | H5: 4300000
A6: 1005 | B6: María López | C6: Diseñadora | D6: 3000000 | E6: 220000 | F6: 160000 | G6: 0 | H6: 3060000
A7: 1006 | B7: Diego Torres | C7: Técnico | D7: 2600000 | E7: 180000 | F7: 120000 | G7: 50000 | H7: 2610000
A8: 1007 | B8: Sofía Ramírez | C8: Recursos Humanos | D8: 3300000 | E8: 240000 | F8: 170000 | G8: 0 | H8: 3370000
A9: 1008 | B9: Andrés Castro | C9: Supervisor | D9: 3800000 | E9: 280000 | F9: 210000 | G9: 0 | H9: 3870000
A10: 1009 | B10: Valentina Ruiz | C10: Secretaria | D10: 2400000 | E10: 150000 | F10: 100000 | G10: 0 | H10: 2450000
A11: 1010 | B11: Mateo Herrera | C11: Ingeniero | D11: 4500000 | E11: 400000 | F11: 300000 | G11: 150000 | H11: 4750000
A12: 1011 | B12: Camila Vargas | C12: Mercadeo | D12: 3100000 | E12: 210000 | F12: 140000 | G12: 0 | H12: 3170000
A13: 1012 | B13: Sebastián Moreno | C13: Vendedor | D13: 2700000 | E13: 190000 | F13: 130000 | G13: 200000 | H13: 2560000
... A21: 1020 | B21: Nicolás Silva | C21: Coordinador | D21: 3900000 | E21: 300000 | F21: 220000 | G21: 0 | H21: 3980000

Sheet Personal
A1: ID Empleado | B1: Nombre | C1: Área | D1: Cargo | E1: Ciudad | F1: Fecha Ingreso | G1: Tipo Contrato
A2: 1001 | B2: Ana Gómez | C2: Administración | D2: Administradora | E2: Bogotá | F2: 2022-02-14 | G2: Indefinido
A3: 1002 | B3: Carlos Pérez | C3: Finanzas | D3: Analista | E3: Medellín | F3: 2021-08-09 | G3: Indefinido
A4: 1003 | B4: Laura Rodríguez | C4: Finanzas | D4: Contadora | E4: Bogotá | F4: 2020-05-18 | G4: Indefinido
A5: 1004 | B5: Juan Martínez | C5: Tecnología | D5: Desarrollador | E5: Cali | F5: 2023-01-23 | G5: Indefinido
A6: 1005 | B6: María López | C6: Diseño | D6: Diseñadora | E6: Bogotá | F6: 2022-07-11 | G6: Indefinido
A7: 1006 | B7: Diego Torres | C7: Operaciones | D7: Técnico | E7: Barranquilla | F7: 2024-03-04 | G7: Término fijo
A8: 1007 | B8: Sofía Ramírez | C8: R.H. | D8: Recursos Humanos | E8: Bogotá | F8: 2021-11-15 | G8: Indefinido
A9: 1008 | B9: Andrés Castro | C9: Operaciones | D9: Supervisor | E9: Medellín | F9: 2019-09-30 | G9: Indefinido
A10: 1009 | B10: Valentina Ruiz | C10: Administración | D10: Secretaria | E10: Cali | F10: 2024-01-08 | G10: Término fijo
A11: 1010 | B11: Mateo Herrera | C11: Ingeniería | D11: Ingeniero | E11: Bogotá | F11: 2018-06-25 | G11: Indefinido
A12: 1011 | B12: Camila Vargas | C12: Mercadeo | D12: Mercadeo | E12: Medellín | F12: 2022-04-12 | G12: Indefinido
A13: 1012 | B13: Sebastián Moreno | C13: Comercial | D13: Vendedor | E13: Cali | F13: 2023-10-02 | G13: Indefinido
... A21: 1020 | B21: Nicolás Silva | C21: Operaciones | D21: Coordinador | E21: Bogotá | F21: 2020-08-17 | G21: Indefinido

Sheet R.H.
A1: ID Empleado | B1: Nombre | C1: Estado | D1: Área | E1: Nivel Desempeño | F1: Última Evaluación | G1: Resultado
A2: 1001 | B2: Ana Gómez | C2: Activa | D2: Administración | E2: Alto | F2: 2026-08-15 | G2: Excelente
A3: 1002 | B3: Carlos Pérez | C3: Activa | D3: Finanzas | E3: Medio | F3: 2026-08-20 | G3: Bueno
A4: 1003 | B4: Laura Rodríguez | C4: Activa | D4: Finanzas | E4: Alto | F4: 2026-08-12 | G4: Excelente
A5: 1004 | B5: Juan Martínez | C5: Activa | D5: Tecnología | E5: Medio | F5: 2026-08-18 | G5: Bueno
A6: 1005 | B6: María López | C6: Activa | D6: Diseño | E6: Medio | F6: 2026-08-21 | G6: Bueno
A7: 1006 | B7: Diego Torres | C7: Activo | D7: Operaciones | E7: Bajo | F7: 2026-08-10 | G7: Bueno
A8: 1007 | B8: Sofía Ramírez | C8: Activa | D8: R.H. | E8: Alto | F8: 2026-08-22 | G8: Excelente
A9: 1008 | B9: Andrés Castro | C9: Activo | D9: Operaciones | E9: Medio | F9: 2026-08-17 | G9: Bueno
A10: 1009 | B10: Valentina Ruiz | C10: Activa | D10: Administración | E10: Medio | F10: 2026-08-14 | G10: Bueno
A11: 1010 | B11: Mateo Herrera | C11: Activo | D11: Ingeniería | E11: Alto | F11: 2026-08-25 | G11: Excelente
A12: 1011 | B12: Camila Vargas | C12: Activa | D12: Mercadeo | E12: Medio | F12: 2026-08-19 | G12: Bueno
A13: 1012 | B13: Sebastián Moreno | C13: Activo | D13: Comercial | E13: Bajo | F13: 2026-08-11 | G13: Bueno
... A21: 1020 | B21: Nicolás Silva | C21: Activo | D21: Operaciones | E21: Alto | F21: 2026-08-27 | G21: Excelente

Sheet Contratacion
A1: ID Empleado | B1: Nombre | C1: Cargo | D1: Fecha Contratación | E1: Tipo Contrato | F1: Nivel Formación | G1: Estado | H1: Fecha Inicio
A2: 1001 | B2: Ana Gómez | C2: Administradora | D2: 2022-02-14 | E2: Indefinido | F2: Profesional | G2: Activa | H2: 2022-02-14
A3: 1002 | B3: Carlos Pérez | C3: Analista | D3: 2021-08-09 | E3: Indefinido | F3: Profesional | G3: Activa | H3: 2021-08-09
A4: 1003 | B4: Laura Rodríguez | C4: Contadora | D4: 2020-05-18 | E4: Indefinido | F4: Profesional | G4: Activa | H4: 2020-05-18
A5: 1004 | B5: Juan Martínez | C5: Desarrollador | D5: 2023-01-23 | E5: Indefinido | F5: Profesional | G5: Activa | H5: 2023-01-23
A6: 1005 | B6: María López | C6: Diseñadora | D6: 2022-07-11 | E6: Indefinido | F6: Profesional | G6: Activa | H6: 2022-07-11
A7: 1006 | B7: Diego Torres | C7: Técnico | D7: 2024-03-04 | E7: Término fijo | F7: Técnico | G7: Activa | H7: 2024-03-04
A8: 1007 | B8: Sofía Ramírez | C8: Recursos Humanos | D8: 2021-11-15 | E8: Indefinido | F8: Profesional | G8: Activa | H8: 2021-11-15
A9: 1008 | B9: Andrés Castro | C9: Supervisor | D9: 2019-09-30 | E9: Indefinido | F9: Tecnólogo | G9: Activa | H9: 2019-09-30
A10: 1009 | B10: Valentina Ruiz | C10: Secretaria | D10: 2024-01-08 | E10: Término fijo | F10: Técnico | G10: Activa | H10: 2024-01-08
A11: 1010 | B11: Mateo Herrera | C11: Ingeniero | D11: 2018-06-25 | E11: Indefinido | F11: Profesional | G11: Activa | H11: 2018-06-25
A12: 1011 | B12: Camila Vargas | C12: Mercadeo | D12: 2022-04-12 | E12: Indefinido | F12: Profesional | G12: Activa | H12: 2022-04-12
A13: 1012 | B13: Sebastián Moreno | C13: Vendedor | D13: 2023-10-02 | E13: Indefinido | F13: Tecnólogo | G13: Activa | H13: 2023-10-02
... A21: 1020 | B21: Nicolás Silva | C21: Coordinador | D21: 2020-08-17 | E21: Indefinido | F21: Profesional | G21: Activa | H21: 2020-08-17

Sheet Consolidado
A1: ID Empleado | B1: Nombre | C1: Área | D1: Cargo | E1: Ciudad | F1: Tipo Contrato | G1: Fecha Ingreso | H1: Nivel Formación | I1: Estado | J1: Nivel Desempeño | K1: Última Evaluación | L1: Resultado | M1: Salario Base | N1: Bonificación | O1: Auxilio | P1: Descuentos | Q1: Neto Pagado
A2: =Personal!A2 -> 1001 | B2: =Personal!B2 -> Ana Gómez | C2: =Personal!C2 -> Administración | D2: =Personal!D2 -> Administradora | E2: =Personal!E2 -> Bogotá | F2: =Personal!G2 -> Indefinido | G2: =Personal!F2 -> 2022-02-14 | H2: =INDEX(Contratacion!$F$2:$F$21,MATCH($A2,Contratacion!$A$2:$A$21,0)) -> Profesional | I2: =INDEX('R.H.'!$C$2:$C$21,MATCH($A2,'R.H.'!$A$2:$A$21,0)) -> Activa | J2: =INDEX('R.H.'!$E$2:$E$21,MATCH($A2,'R.H.'!$A$2:$A$21,0)) -> Alto | K2: =INDEX('R.H.'!$F$2:$F$21,MATCH($A2,'R.H.'!$A$2:$A$21,0)) -> 2026-08-15 | L2: =INDEX('R.H.'!$G$2:$G$21,MATCH($A2,'R.H.'!$A$2:$A$21,0)) -> Excelente | M2: =INDEX(Nomina!$D$2:$D$21,MATCH($A2,Nomina!$A$2:$A$21,0)) -> 2800000 | N2: =INDEX(Nomina!$E$2:$E$21,MATCH($A2,Nomina!$A$2:$A$21,0)) -> 200000 | O2: =INDEX(Nomina!$F$2:$F$21,MATCH($A2,Nomina!$A$2:$A$21,0)) -> 150000 | P2: =INDEX(Nomina!$G$2:$G$21,MATCH($A2,Nomina!$A$2:$A$21,0)) -> 0 | Q2: =INDEX(Nomina!$H$2:$H$21,MATCH($A2,Nomina!$A$2:$A$21,0)) -> 2850000
A3: =Personal!A3 -> 1002 | B3: =Personal!B3 -> Carlos Pérez | C3: =Personal!C3 -> Finanzas | D3: =Personal!D3 -> Analista | E3: =Personal!E3 -> Medellín | F3: =Personal!G3 -> Indefinido | G3: =Personal!F3 -> 2021-08-09 | H3: =INDEX(Contratacion!$F$2:$F$21,MATCH($A3,Contratacion!$A$2:$A$21,0)) -> Profesional | I3: =INDEX('R.H.'!$C$2:$C$21,MATCH($A3,'R.H.'!$A$2:$A$21,0)) -> Activa | J3: =INDEX('R.H.'!$E$2:$E$21,MATCH($A3,'R.H.'!$A$2:$A$21,0)) -> Medio | K3: =INDEX('R.H.'!$F$2:$F$21,MATCH($A3,'R.H.'!$A$2:$A$21,0)) -> 2026-08-20 | L3: =INDEX('R.H.'!$G$2:$G$21,MATCH($A3,'R.H.'!$A$2:$A$21,0)) -> Bueno | M3: =INDEX(Nomina!$D$2:$D$21,MATCH($A3,Nomina!$A$2:$A$21,0)) -> 3200000 | N3: =INDEX(Nomina!$E$2:$E$21,MATCH($A3,Nomina!$A$2:$A$21,0)) -> 250000 | O3: =INDEX(Nomina!$F$2:$F$21,MATCH($A3,Nomina!$A$2:$A$21,0)) -> 180000 | P3: =INDEX(Nomina!$G$2:$G$21,MATCH($A3,Nomina!$A$2:$A$21,0)) -> 0 | Q3: =INDEX(Nomina!$H$2:$H$21,MATCH($A3,Nomina!$A$2:$A$21,0)) -> 3270000
A4: =Personal!A4 -> 1003 | B4: =Personal!B4 -> Laura Rodríguez | C4: =Personal!C4 -> Finanzas | D4: =Personal!D4 -> Contadora | E4: =Personal!E4 -> Bogotá | F4: =Personal!G4 -> Indefinido | G4: =Personal!F4 -> 2020-05-18 | H4: =INDEX(Contratacion!$F$2:$F$21,MATCH($A4,Contratacion!$A$2:$A$21,0)) -> Profesional | I4: =INDEX('R.H.'!$C$2:$C$21,MATCH($A4,'R.H.'!$A$2:$A$21,0)) -> Activa | J4: =INDEX('R.H.'!$E$2:$E$21,MATCH($A4,'R.H.'!$A$2:$A$21,0)) -> Alto | K4: =INDEX('R.H.'!$F$2:$F$21,MATCH($A4,'R.H.'!$A$2:$A$21,0)) -> 2026-08-12 | L4: =INDEX('R.H.'!$G$2:$G$21,MATCH($A4,'R.H.'!$A$2:$A$21,0)) -> Excelente | M4: =INDEX(Nomina!$D$2:$D$21,MATCH($A4,Nomina!$A$2:$A$21,0)) -> 3500000 | N4: =INDEX(Nomina!$E$2:$E$21,MATCH($A4,Nomina!$A$2:$A$21,0)) -> 300000 | O4: =INDEX(Nomina!$F$2:$F$21,MATCH($A4,Nomina!$A$2:$A$21,0)) -> 200000 | P4: =INDEX(Nomina!$G$2:$G$21,MATCH($A4,Nomina!$A$2:$A$21,0)) -> 100000 | Q4: =INDEX(Nomina!$H$2:$H$21,MATCH($A4,Nomina!$A$2:$A$21,0)) -> 3500000
A5: =Personal!A5 -> 1004 | B5: =Personal!B5 -> Juan Martínez | C5: =Personal!C5 -> Tecnología | D5: =Personal!D5 -> Desarrollador | E5: =Personal!E5 -> Cali | F5: =Personal!G5 -> Indefinido | G5: =Personal!F5 -> 2023-01-23 | H5: =INDEX(Contratacion!$F$2:$F$21,MATCH($A5,Contratacion!$A$2:$A$21,0)) -> Profesional | I5: =INDEX('R.H.'!$C$2:$C$21,MATCH($A5,'R.H.'!$A$2:$A$21,0)) -> Activa | J5: =INDEX('R.H.'!$E$2:$E$21,MATCH($A5,'R.H.'!$A$2:$A$21,0)) -> Medio | K5: =INDEX('R.H.'!$F$2:$F$21,MATCH($A5,'R.H.'!$A$2:$A$21,0)) -> 2026-08-18 | L5: =INDEX('R.H.'!$G$2:$G$21,MATCH($A5,'R.H.'!$A$2:$A$21,0)) -> Bueno | M5: =INDEX(Nomina!$D$2:$D$21,MATCH($A5,Nomina!$A$2:$A$21,0)) -> 4200000 | N5: =INDEX(Nomina!$E$2:$E$21,MATCH($A5,Nomina!$A$2:$A$21,0)) -> 350000 | O5: =INDEX(Nomina!$F$2:$F$21,MATCH($A5,Nomina!$A$2:$A$21,0)) -> 250000 | P5: =INDEX(Nomina!$G$2:$G$21,MATCH($A5,Nomina!$A$2:$A$21,0)) -> 0 | Q5: =INDEX(Nomina!$H$2:$H$21,MATCH($A5,Nomina!$A$2:$A$21,0)) -> 4300000
A6: =Personal!A6 -> 1005 | B6: =Personal!B6 -> María López | C6: =Personal!C6 -> Diseño | D6: =Personal!D6 -> Diseñadora | E6: =Personal!E6 -> Bogotá | F6: =Personal!G6 -> Indefinido | G6: =Personal!F6 -> 2022-07-11 | H6: =INDEX(Contratacion!$F$2:$F$21,MATCH($A6,Contratacion!$A$2:$A$21,0)) -> Profesional | I6: =INDEX('R.H.'!$C$2:$C$21,MATCH($A6,'R.H.'!$A$2:$A$21,0)) -> Activa | J6: =INDEX('R.H.'!$E$2:$E$21,MATCH($A6,'R.H.'!$A$2:$A$21,0)) -> Medio | K6: =INDEX('R.H.'!$F$2:$F$21,MATCH($A6,'R.H.'!$A$2:$A$21,0)) -> 2026-08-21 | L6: =INDEX('R.H.'!$G$2:$G$21,MATCH($A6,'R.H.'!$A$2:$A$21,0)) -> Bueno | M6: =INDEX(Nomina!$D$2:$D$21,MATCH($A6,Nomina!$A$2:$A$21,0)) -> 3000000 | N6: =INDEX(Nomina!$E$2:$E$21,MATCH($A6,Nomina!$A$2:$A$21,0)) -> 220000 | O6: =INDEX(Nomina!$F$2:$F$21,MATCH($A6,Nomina!$A$2:$A$21,0)) -> 160000 | P6: =INDEX(Nomina!$G$2:$G$21,MATCH($A6,Nomina!$A$2:$A$21,0)) -> 0 | Q6: =INDEX(Nomina!$H$2:$H$21,MATCH($A6,Nomina!$A$2:$A$21,0)) -> 3060000
A7: =Personal!A7 -> 1006 | B7: =Personal!B7 -> Diego Torres | C7: =Personal!C7 -> Operaciones | D7: =Personal!D7 -> Técnico | E7: =Personal!E7 -> Barranquilla | F7: =Personal!G7 -> Término fijo | G7: =Personal!F7 -> 2024-03-04 | H7: =INDEX(Contratacion!$F$2:$F$21,MATCH($A7,Contratacion!$A$2:$A$21,0)) -> Técnico | I7: =INDEX('R.H.'!$C$2:$C$21,MATCH($A7,'R.H.'!$A$2:$A$21,0)) -> Activo | J7: =INDEX('R.H.'!$E$2:$E$21,MATCH($A7,'R.H.'!$A$2:$A$21,0)) -> Bajo | K7: =INDEX('R.H.'!$F$2:$F$21,MATCH($A7,'R.H.'!$A$2:$A$21,0)) -> 2026-08-10 | L7: =INDEX('R.H.'!$G$2:$G$21,MATCH($A7,'R.H.'!$A$2:$A$21,0)) -> Bueno | M7: =INDEX(Nomina!$D$2:$D$21,MATCH($A7,Nomina!$A$2:$A$21,0)) -> 2600000 | N7: =INDEX(Nomina!$E$2:$E$21,MATCH($A7,Nomina!$A$2:$A$21,0)) -> 180000 | O7: =INDEX(Nomina!$F$2:$F$21,MATCH($A7,Nomina!$A$2:$A$21,0)) -> 120000 | P7: =INDEX(Nomina!$G$2:$G$21,MATCH($A7,Nomina!$A$2:$A$21,0)) -> 50000 | Q7: =INDEX(Nomina!$H$2:$H$21,MATCH($A7,Nomina!$A$2:$A$21,0)) -> 2610000
A8: =Personal!A8 -> 1007 | B8: =Personal!B8 -> Sofía Ramírez | C8: =Personal!C8 -> R.H. | D8: =Personal!D8 -> Recursos Humanos | E8: =Personal!E8 -> Bogotá | F8: =Personal!G8 -> Indefinido | G8: =Personal!F8 -> 2021-11-15 | H8: =INDEX(Contratacion!$F$2:$F$21,MATCH($A8,Contratacion!$A$2:$A$21,0)) -> Profesional | I8: =INDEX('R.H.'!$C$2:$C$21,MATCH($A8,'R.H.'!$A$2:$A$21,0)) -> Activa | J8: =INDEX('R.H.'!$E$2:$E$21,MATCH($A8,'R.H.'!$A$2:$A$21,0)) -> Alto | K8: =INDEX('R.H.'!$F$2:$F$21,MATCH($A8,'R.H.'!$A$2:$A$21,0)) -> 2026-08-22 | L8: =INDEX('R.H.'!$G$2:$G$21,MATCH($A8,'R.H.'!$A$2:$A$21,0)) -> Excelente | M8: =INDEX(Nomina!$D$2:$D$21,MATCH($A8,Nomina!$A$2:$A$21,0)) -> 3300000 | N8: =INDEX(Nomina!$E$2:$E$21,MATCH($A8,Nomina!$A$2:$A$21,0)) -> 240000 | O8: =INDEX(Nomina!$F$2:$F$21,MATCH($A8,Nomina!$A$2:$A$21,0)) -> 170000 | P8: =INDEX(Nomina!$G$2:$G$21,MATCH($A8,Nomina!$A$2:$A$21,0)) -> 0 | Q8: =INDEX(Nomina!$H$2:$H$21,MATCH($A8,Nomina!$A$2:$A$21,0)) -> 3370000
A9: =Personal!A9 -> 1008 | B9: =Personal!B9 -> Andrés Castro | C9: =Personal!C9 -> Operaciones | D9: =Personal!D9 -> Supervisor | E9: =Personal!E9 -> Medellín | F9: =Personal!G9 -> Indefinido | G9: =Personal!F9 -> 2019-09-30 | H9: =INDEX(Contratacion!$F$2:$F$21,MATCH($A9,Contratacion!$A$2:$A$21,0)) -> Tecnólogo | I9: =INDEX('R.H.'!$C$2:$C$21,MATCH($A9,'R.H.'!$A$2:$A$21,0)) -> Activo | J9: =INDEX('R.H.'!$E$2:$E$21,MATCH($A9,'R.H.'!$A$2:$A$21,0)) -> Medio | K9: =INDEX('R.H.'!$F$2:$F$21,MATCH($A9,'R.H.'!$A$2:$A$21,0)) -> 2026-08-17 | L9: =INDEX('R.H.'!$G$2:$G$21,MATCH($A9,'R.H.'!$A$2:$A$21,0)) -> Bueno | M9: =INDEX(Nomina!$D$2:$D$21,MATCH($A9,Nomina!$A$2:$A$21,0)) -> 3800000 | N9: =INDEX(Nomina!$E$2:$E$21,MATCH($A9,Nomina!$A$2:$A$21,0)) -> 280000 | O9: =INDEX(Nomina!$F$2:$F$21,MATCH($A9,Nomina!$A$2:$A$21,0)) -> 210000 | P9: =INDEX(Nomina!$G$2:$G$21,MATCH($A9,Nomina!$A$2:$A$21,0)) -> 0 | Q9: =INDEX(Nomina!$H$2:$H$21,MATCH($A9,Nomina!$A$2:$A$21,0)) -> 3870000
A10: =Personal!A10 -> 1009 | B10: =Personal!B10 -> Valentina Ruiz | C10: =Personal!C10 -> Administración | D10: =Personal!D10 -> Secretaria | E10: =Personal!E10 -> Cali | F10: =Personal!G10 -> Término fijo | G10: =Personal!F10 -> 2024-01-08 | H10: =INDEX(Contratacion!$F$2:$F$21,MATCH($A10,Contratacion!$A$2:$A$21,0)) -> Técnico | I10: =INDEX('R.H.'!$C$2:$C$21,MATCH($A10,'R.H.'!$A$2:$A$21,0)) -> Activa | J10: =INDEX('R.H.'!$E$2:$E$21,MATCH($A10,'R.H.'!$A$2:$A$21,0)) -> Medio | K10: =INDEX('R.H.'!$F$2:$F$21,MATCH($A10,'R.H.'!$A$2:$A$21,0)) -> 2026-08-14 | L10: =INDEX('R.H.'!$G$2:$G$21,MATCH($A10,'R.H.'!$A$2:$A$21,0)) -> Bueno | M10: =INDEX(Nomina!$D$2:$D$21,MATCH($A10,Nomina!$A$2:$A$21,0)) -> 2400000 | N10: =INDEX(Nomina!$E$2:$E$21,MATCH($A10,Nomina!$A$2:$A$21,0)) -> 150000 | O10: =INDEX(Nomina!$F$2:$F$21,MATCH($A10,Nomina!$A$2:$A$21,0)) -> 100000 | P10: =INDEX(Nomina!$G$2:$G$21,MATCH($A10,Nomina!$A$2:$A$21,0)) -> 0 | Q10: =INDEX(Nomina!$H$2:$H$21,MATCH($A10,Nomina!$A$2:$A$21,0)) -> 2450000
A11: =Personal!A11 -> 1010 | B11: =Personal!B11 -> Mateo Herrera | C11: =Personal!C11 -> Ingeniería | D11: =Personal!D11 -> Ingeniero | E11: =Personal!E11 -> Bogotá | F11: =Personal!G11 -> Indefinido | G11: =Personal!F11 -> 2018-06-25 | H11: =INDEX(Contratacion!$F$2:$F$21,MATCH($A11,Contratacion!$A$2:$A$21,0)) -> Profesional | I11: =INDEX('R.H.'!$C$2:$C$21,MATCH($A11,'R.H.'!$A$2:$A$21,0)) -> Activo | J11: =INDEX('R.H.'!$E$2:$E$21,MATCH($A11,'R.H.'!$A$2:$A$21,0)) -> Alto | K11: =INDEX('R.H.'!$F$2:$F$21,MATCH($A11,'R.H.'!$A$2:$A$21,0)) -> 2026-08-25 | L11: =INDEX('R.H.'!$G$2:$G$21,MATCH($A11,'R.H.'!$A$2:$A$21,0)) -> Excelente | M11: =INDEX(Nomina!$D$2:$D$21,MATCH($A11,Nomina!$A$2:$A$21,0)) -> 4500000 | N11: =INDEX(Nomina!$E$2:$E$21,MATCH($A11,Nomina!$A$2:$A$21,0)) -> 400000 | O11: =INDEX(Nomina!$F$2:$F$21,MATCH($A11,Nomina!$A$2:$A$21,0)) -> 300000 | P11: =INDEX(Nomina!$G$2:$G$21,MATCH($A11,Nomina!$A$2:$A$21,0)) -> 150000 | Q11: =INDEX(Nomina!$H$2:$H$21,MATCH($A11,Nomina!$A$2:$A$21,0)) -> 4750000
A12: =Personal!A12 -> 1011 | B12: =Personal!B12 -> Camila Vargas | C12: =Personal!C12 -> Mercadeo | D12: =Personal!D12 -> Mercadeo | E12: =Personal!E12 -> Medellín | F12: =Personal!G12 -> Indefinido | G12: =Personal!F12 -> 2022-04-12 | H12: =INDEX(Contratacion!$F$2:$F$21,MATCH($A12,Contratacion!$A$2:$A$21,0)) -> Profesional | I12: =INDEX('R.H.'!$C$2:$C$21,MATCH($A12,'R.H.'!$A$2:$A$21,0)) -> Activa | J12: =INDEX('R.H.'!$E$2:$E$21,MATCH($A12,'R.H.'!$A$2:$A$21,0)) -> Medio | K12: =INDEX('R.H.'!$F$2:$F$21,MATCH($A12,'R.H.'!$A$2:$A$21,0)) -> 2026-08-19 | L12: =INDEX('R.H.'!$G$2:$G$21,MATCH($A12,'R.H.'!$A$2:$A$21,0)) -> Bueno | M12: =INDEX(Nomina!$D$2:$D$21,MATCH($A12,Nomina!$A$2:$A$21,0)) -> 3100000 | N12: =INDEX(Nomina!$E$2:$E$21,MATCH($A12,Nomina!$A$2:$A$21,0)) -> 210000 | O12: =INDEX(Nomina!$F$2:$F$21,MATCH($A12,Nomina!$A$2:$A$21,0)) -> 140000 | P12: =INDEX(Nomina!$G$2:$G$21,MATCH($A12,Nomina!$A$2:$A$21,0)) -> 0 | Q12: =INDEX(Nomina!$H$2:$H$21,MATCH($A12,Nomina!$A$2:$A$21,0)) -> 3170000
A13: =Personal!A13 -> 1012 | B13: =Personal!B13 -> Sebastián Moreno | C13: =Personal!C13 -> Comercial | D13: =Personal!D13 -> Vendedor | E13: =Personal!E13 -> Cali | F13: =Personal!G13 -> Indefinido | G13: =Personal!F13 -> 2023-10-02 | H13: =INDEX(Contratacion!$F$2:$F$21,MATCH($A13,Contratacion!$A$2:$A$21,0)) -> Tecnólogo | I13: =INDEX('R.H.'!$C$2:$C$21,MATCH($A13,'R.H.'!$A$2:$A$21,0)) -> Activo | J13: =INDEX('R.H.'!$E$2:$E$21,MATCH($A13,'R.H.'!$A$2:$A$21,0)) -> Bajo | K13: =INDEX('R.H.'!$F$2:$F$21,MATCH($A13,'R.H.'!$A$2:$A$21,0)) -> 2026-08-11 | L13: =INDEX('R.H.'!$G$2:$G$21,MATCH($A13,'R.H.'!$A$2:$A$21,0)) -> Bueno | M13: =INDEX(Nomina!$D$2:$D$21,MATCH($A13,Nomina!$A$2:$A$21,0)) -> 2700000 | N13: =INDEX(Nomina!$E$2:$E$21,MATCH($A13,Nomina!$A$2:$A$21,0)) -> 190000 | O13: =INDEX(Nomina!$F$2:$F$21,MATCH($A13,Nomina!$A$2:$A$21,0)) -> 130000 | P13: =INDEX(Nomina!$G$2:$G$21,MATCH($A13,Nomina!$A$2:$A$21,0)) -> 200000 | Q13: =INDEX(Nomina!$H$2:$H$21,MATCH($A13,Nomina!$A$2:$A$21,0)) -> 2560000
... A21: =Personal!A21 -> 1020 | B21: =Personal!B21 -> Nicolás Silva | C21: =Personal!C21 -> Operaciones | D21: =Personal!D21 -> Coordinador | E21: =Personal!E21 -> Bogotá | F21: =Personal!G21 -> Indefinido | G21: =Personal!F21 -> 2020-08-17 | H21: =INDEX(Contratacion!$F$2:$F$21,MATCH($A21,Contratacion!$A$2:$A$21,0)) -> Profesional | I21: =INDEX('R.H.'!$C$2:$C$21,MATCH($A21,'R.H.'!$A$2:$A$21,0)) -> Activo | J21: =INDEX('R.H.'!$E$2:$E$21,MATCH($A21,'R.H.'!$A$2:$A$21,0)) -> Alto | K21: =INDEX('R.H.'!$F$2:$F$21,MATCH($A21,'R.H.'!$A$2:$A$21,0)) -> 2026-08-27 | L21: =INDEX('R.H.'!$G$2:$G$21,MATCH($A21,'R.H.'!$A$2:$A$21,0)) -> Excelente | M21: =INDEX(Nomina!$D$2:$D$21,MATCH($A21,Nomina!$A$2:$A$21,0)) -> 3900000 | N21: =INDEX(Nomina!$E$2:$E$21,MATCH($A21,Nomina!$A$2:$A$21,0)) -> 300000 | O21: =INDEX(Nomina!$F$2:$F$21,MATCH($A21,Nomina!$A$2:$A$21,0)) -> 220000 | P21: =INDEX(Nomina!$G$2:$G$21,MATCH($A21,Nomina!$A$2:$A$21,0)) -> 0 | Q21: =INDEX(Nomina!$H$2:$H$21,MATCH($A21,Nomina!$A$2:$A$21,0)) -> 3980000
